Metadata-Version: 2.1
Name: fproperty
Version: 0.1.0
Summary: fproperty
Home-page: http://github.com/serwy/fproperty
Author: Roger D. Serwy
Author-email: roger.serwy@gmail.com
License: UNKNOWN
Platform: UNKNOWN
Classifier: Development Status :: 4 - Beta
Classifier: License :: OSI Approved :: Apache Software License
Classifier: Operating System :: OS Independent
Classifier: Programming Language :: Python :: 2.7
Classifier: Programming Language :: Python :: 3
